Workbook

Sheet Read Me
B2: Play the Games — Cost-Benefit Analysis (AUD)
B4: Purpose | C4: This workbook estimates costs and revenue for the Play the Games sponsor-funded, prize-driven mobile gaming platform across the 2027-2034 rollout (Pilot -> Domestic Scale -> International Push -> Pre-Olympic -> Brisbane 2032 Games -> Post-Games Licensing). All figures are in Australian Dollars (AUD).
B6: How to read this workbook
B7: Assumptions sheet | C7: Every input used anywhere in the model lives here, in blue font, with a stated rationale and a source citation. Change a number here and it flows through to every other tab.
B8: Color coding | C8: Blue = hardcoded input/assumption. Black = formula/calculation. Green = link pulling from another sheet. Yellow highlight = an assumption you may want to revisit or negotiate (e.g. revenue share %).
B9: Cost Build-Up sheet | C9: Year-by-year cost breakdown (platform build, infrastructure, content, legal, BD/sales, operations) for 2027-2034.
B10: Revenue Build-Up sheet | C10: Year-by-year revenue breakdown (sponsorship inventory, concession uplift share, licensing fees post-2032) for 2027-2034.
B11: Cost-Benefit Summary sheet | C11: Combines cost and revenue into net position, cumulative cash flow, and a simple payback view.
B12: Sources sheet | C12: Full reference list for every external figure used as a benchmark or proxy in this model.
B14: Important caveat | C14: Play the Games is a new, unbuilt concept with no direct comparable product operating at this scale in Australia. Where no direct precedent exists, this model uses the closest available real-world proxy (e.g. comparable stadium digital advertising inventory, comparable MVP/app build costs, comparable fan-engagement platform benchmarks) and states this explicitly in the rationale and source columns. All figures should be treated as a planning estimate to be refined with real quotes and a negotiated revenue share once venue/sponsor conversations begin (see Assumptions sheet, row for Revenue Share %, highlighted in yellow).

Sheet Assumptions
B2: Key Assumptions & Sources
B4: Assumption | C4: Value | D4: Rationale | E4: Source
B5: CATEGORY: Rollout & Venue Scale
B6: Pilot year | C6: 2027 | D6: First operating year; aligns with team plan to pilot with Queensland Stadiums before scaling. | E6: Team project plan (GIC 2026 brief)
B7: Pilot venues (2027) | C7: 3 | D7: Suncorp Stadium, The Gabba, Brisbane Entertainment Centre — representative Queensland Stadiums venues for an initial AFL/NRL pilot. | E7: Team project plan
B8: Domestic venues by 2031 (pre-Olympic) | C8: 20 | D8: Gradual expansion across Queensland and interstate AFL/NRL/Cricket venues ahead of the Games. | E8: Team project plan; phased rollout logic
B9: Olympic venues (2032) | C9: 37 | D9: Official Brisbane 2032 venue count as stated in project brief. | E9: Brisbane 2032 GIC project brief
B10: Olympic competition days | C10: 17 | D10: Standard Olympic Games competition window. | E10: Brisbane 2032 GIC project brief
B11: Olympic tickets sold | C11: 9500000 | D11: Stated total ticket volume across the Games. | E11: Brisbane 2032 GIC project brief
B12: CATEGORY: Game Sessions & Sponsorship Fee
B13: Domestic events per venue per year | C13: 20 | D13: Approximate AFL/NRL home-game season length per venue. | E13: Standard AFL/NRL season length (industry knowledge)
B14: Dead-time sessions per event | C14: 1 | D14: half-time/main break | E14: Team project plan; matches NFL/NBA-style game structure
B15: Domestic sponsorship fee per session (2027) | C15: 2000 | D15: Positioned as entry-level digital in-venue inventory — well below mid-tier LED/jumbotron rotation pricing ($10k-$100k/season) to reflect an unproven, pilot-stage product. | E15: Benchmarked against AdQuick stadium advertising cost guide (in-seat/entry-level placements from ~$1,000/game; digital scoreboard/jumbotron $10k-$100k per SEASON) — https://www.adquick.com/stadium-advertising
B16: Domestic sponsorship fee per session (2028+, escalated) | C16: 3000 | D16: Fee increases once the pilot has proof points and the product is positioned alongside major tournaments (RWC 2027, T20 WC 2028) with larger audiences. | E16: Same benchmark as above, escalated toward mid-tier LED rotation pricing range
B17: Olympic sponsorship fee per session (2032) | C17: 10000 | D17: Premium Olympic-scale rate reflecting global broadcast exposure and the scarcity/prestige of official Games inventory — positioned toward the lower-mid end of premium digital perimeter/LED inventory used by top-tier venues. | E17: Benchmarked against SoFi Stadium/Crypto.com Arena premium digital board pricing ($75k-$300k PER SEASON, i.e. ~$2.5k-$10k per game-equivalent) — https://www.losangelesstadiumadvertising.com (Carvertise) and DOIT Vision LED cost guide ($6,000-$15,000 per game) — https://www.doitvision.com/how-much-does-perimeter-led-display-cost/
B18: CATEGORY: Revenue Share & Licensing
B19: Play the Games revenue share of sponsorship inventory | C19: 0.2 | D19: PLACEHOLDER — to be negotiated per venue. 20% is a conservative mid-point for a third-party technology/inventory partner contributing the platform but not owning the underlying venue relationship; final % will vary by venue and should be revisited once commercial terms are discussed. | E19: Placeholder estimate — no public benchmark exists for this specific arrangement; flagged for negotiation (see Read Me sheet)
B20: Concession revenue share (uplift attributable to platform) | C20: 0.1 | D20: Conservative share of incremental concession spend directly attributable to in-app redemption offers, reflecting that Play the Games drives but does not operate the point-of-sale. | E20: Placeholder estimate — directional only, consistent with third-party referral/influencer commercial structures
B21: Avg. redemption rate (active users who redeem a prize) | C21: 0.2 | D21: Mid-point of a plausible 15-25% range cited in the original project brief for location-aware, game-won discounts. | E21: Team project plan (PlayLympics brief, "Pay-Using-Benefit Criteria" section)
B22: Avg. concession transaction value per redemption (AUD) | C22: 12 | D22: Typical single-item stadium F&B transaction value (e.g. a drink or snack voucher). | E22: Estimate based on typical Australian stadium concession pricing; directional only
B23: AFL annual licensing fee (post-2032) | C23: 500000 | D23: Mid-market enterprise software/platform licensing fee for a national-code year-round deployment, escalated from the lower end given AFL venue count and audience scale. | E23: Benchmarked against TechAhead "Enterprise Platform" pricing tier ($250k-$500k+) — https://www.techaheadcorp.com/blog/mobile-app-development-cost-guide/ ; figure represents annual licence not build cost
B24: NRL annual licensing fee (post-2032) | C24: 500000 | D24: Same logic as AFL — comparable national code scale. | E24: Same benchmark as above
B25: Cricket Australia annual licensing fee (post-2032) | C25: 300000 | D25: Smaller relative venue footprint and shorter domestic season than AFL/NRL. | E25: Directional estimate, scaled down from AFL/NRL benchmark
B26: International/other code licensing fee (post-2032, combined) | C26: 400000 | D26: 2-3 additional codes/leagues at smaller individual licence values, combined. | E26: Directional estimate
B27: CATEGORY: Platform Build & Technology Costs
B28: Initial platform build (PWA + backend) — Year 1 | C28: =2*20*8*60 -> 19200 | D28: Positioned at the mid-point of a "Proof of Concept / MVP" tier mobile-web build — single platform (PWA, not native app), basic backend, core screens — consistent with team brief specifying a mobile-optimised website rather than a native app. | E28: 2 engineers, 4 weeks, 8hrs/day, 60AUD
B29: Annual platform maintenance (% of build cost) | C29: 0.2 | D29: Industry-standard ongoing maintenance allowance. | E29: https://www.cynoteck.com/blog-post/mobile-app-development-cost
B30: Game Design (per venue per year) | C30: =2*16*60 -> 1920 | E30: 2 engineers, 16hrs, 60AUD
B31: CATEGORY: Cost Escalation
B32: General cost escalation per phase (non-platform opex) | C32: 0.15 | D32: Reflects growing operational complexity (more venues, more languages, more events) at each rollout phase rather than flat annual inflation. | E32: Directional planning assumption, consistent with team phased rollout plan (Pilot -> Scale -> Games -> Sustain)

Sheet Cost Build-Up
A1: Cost Build-Up by Year (AUD)
A3: Cost Item | B3: 2026 | C3: 2027 | D3: 2028 | E3: 2029 | F3: 2030 | G3: 2031 | H3: 2032 | I3: 2033 | J3: 2034 | K3: 2035 | L3: Notes / Source
A4: Subtotal - One-Time Platform Build | B4: 76000 | L4: https://www.cynoteck.com/blog-post/mobile-app-development-cost
A6: Platform maintenance (% of total build cost) | B6: 2000 | C6: =$B$4*Assumptions!$C$29 -> 15200 | D6: =$B$4*Assumptions!$C$29 -> 15200 | E6: =$B$4*Assumptions!$C$29 -> 15200 | F6: =$B$4*Assumptions!$C$29 -> 15200 | G6: =$B$4*Assumptions!$C$29 -> 15200 | H6: =$B$4*Assumptions!$C$29 -> 15200 | I6: =$B$4*Assumptions!$C$29 -> 15200 | J6: =$B$4*Assumptions!$C$29 -> 15200 | K6: =$B$4*Assumptions!$C$29 -> 15200 | L6: 20% of one-time build cost per year, from Year 2 onward. https://www.cynoteck.com/blog-post/mobile-app-development-cost
A8: Cloud infrastructure | B8: 20000 | C8: 20000 | D8: 20000 | E8: 20000 | F8: 20000 | G8: 20000 | H8: 70000 | I8: 40000 | J8: 40000 | K8: 40000 | L8: Scales with simultaneous user load; spikes in 2032 for ~30,000+ concurrent Olympic users. https://robocitrus.com/blog/laufende-app-kosten
A9: Legal & compliance (venue contracts, Privacy Act) | B9: 15000 | C9: 15000 | D9: 20000 | E9: 20000 | F9: 35000 | G9: 50000 | H9: 50000 | I9: 35000 | J9: 35000 | K9: 35000 | L9: Covers revenue-share contracts, Australian Privacy Act compliance, and (from 2030) international/OCOG-level agreements. https://sprintlaw.com.au/articles/how-mu%EE%80%80ch-does-legal-advice-cost-for-small-busi%EE%80%80nesses-and-startups/
A10: Insurance | B10: 2000 | C10: 2000 | D10: 2000 | E10: 2000 | F10: 2000 | G10: 2000 | H10: 2000 | I10: 2000 | J10: 2000 | K10: 2000 | L10: https://nationalcover.com.au/business-insurance-for-startups/
A11: Business development & sales | B11: 30000 | C11: 30000 | D11: 40000 | E11: 50000 | F11: 70000 | G11: 60000 | H11: 0 | I11: 20000 | J11: 20000 | K11: 20000 | L11: Venue/sponsor acquisition effort; assumed to taper in 2032 (focus shifts to delivery) and resume for post-Games licensing conversations. Directional estimate.
A12: Team Saleries | B12: =C12/2 -> 200000 | C12: =5*80000 -> 400000 | D12: =5*80000 -> 400000 | E12: =5*80000 -> 400000 | F12: =5*80000 -> 400000 | G12: =5*80000 -> 400000 | H12: =5*80000 -> 400000 | I12: =5*80000 -> 400000 | J12: =5*80000 -> 400000 | K12: =5*80000 -> 400000 | L12: Includes venue onboarding, QR placement coordination, and (2032) on-site staffing across 37 venues x 17 days. Directional estimate.
A13: Hardware & Applications | B13: =5*500*6 -> 15000 | C13: =5*500*12 -> 30000 | D13: =5*500*12 -> 30000 | E13: =5*500*12 -> 30000 | F13: =5*500*12 -> 30000 | G13: =5*500*12 -> 30000 | H13: =5*500*12 -> 30000 | I13: =5*500*12 -> 30000 | J13: =5*500*12 -> 30000 | K13: =5*500*12 -> 30000 | L13: Includes rented Laptops, Home Office material, Software; https://www.goworkwize.com/blog/it-equipment-average-cost; https://www.goworkwize.com/blog/it-equipment-average-cost
A16: TOTAL ANNUAL COST | B16: =SUM(B4:B13) -> 360000 | C16: =SUM(C4:C13) -> 512200 | D16: =SUM(D4:D13) -> 527200 | E16: =SUM(E4:E13) -> 537200 | F16: =SUM(F4:F13) -> 572200 | G16: =SUM(G4:G13) -> 577200 | H16: =SUM(H4:H13) -> 567200 | I16: =SUM(I4:I13) -> 542200 | ... K16: =SUM(K4:K13) -> 542200

Sheet Revenue Build-Up
B2: Revenue Build-Up by Year (AUD)
B4: Revenue Driver | C4: 2027 | D4: 2028 | E4: 2029 | F4: 2030 | G4: 2031 | H4: 2032 | I4: 2033 | J4: 2034 | K4: Notes / Source
B5: Domestic venues active | C5: 3 | D5: 6 | E5: 10 | F5: 15 | G5: 20 | H5: 0 | I5: 0 | J5: 0 | K5: Phased domestic rollout: 3 (2027 QLD pilot) -> 6 -> 10 -> 15 -> 20 by 2031. Set to 0 in 2032 (Games year handled separately below) and resumes implicitly via licensing from 2033.
B6: Domestic events per venue per year | C6: =Assumptions!$C$13 -> 20 | D6: =Assumptions!$C$13 -> 20 | E6: =Assumptions!$C$13 -> 20 | F6: =Assumptions!$C$13 -> 20 | G6: =Assumptions!$C$13 -> 20 | H6: =Assumptions!$C$13 -> 20 | I6: =Assumptions!$C$13 -> 20 | J6: =Assumptions!$C$13 -> 20 | K6: AFL/NRL-style home season length. See Assumptions.
B7: Extra major-tournament matches (RWC 2027 carry-over, T20 WC 2028, Women's RWC 2029) | C7: 0 | D7: 70 | E7: 25 | F7: 0 | G7: 0 | H7: 0 | I7: 0 | J7: 0 | K7: 2028: ~40 Rugby World Cup 2027 carry-over/related matches + ~30 T20 Cricket World Cup matches on Australian soil. 2029: ~25 Women's Rugby World Cup Australia matches. Match counts are directional planning estimates, not official fixture counts.
B8: Sessions per event (dead-time windows) | C8: =Assumptions!$C$14 -> 1 | D8: =Assumptions!$C$14 -> 1 | E8: =Assumptions!$C$14 -> 1 | F8: =Assumptions!$C$14 -> 1 | G8: =Assumptions!$C$14 -> 1 | H8: =Assumptions!$C$14 -> 1 | I8: =Assumptions!$C$14 -> 1 | J8: =Assumptions!$C$14 -> 1
B9: Sponsorship fee per session (AUD) | C9: =Assumptions!$C$15 -> 2000 | D9: =Assumptions!$C$16 -> 3000 | E9: =Assumptions!$C$16 -> 3000 | F9: =Assumptions!$C$16 -> 3000 | G9: =Assumptions!$C$16 -> 3000 | H9: =Assumptions!$C$17 -> 10000 | I9: =Assumptions!$C$16 -> 3000 | J9: =Assumptions!$C$16 -> 3000 | K9: 2027 entry rate; escalates 2028+; premium Olympic rate in 2032. See Assumptions for benchmarks.
B10: Domestic sponsorship inventory (venues x events x sessions x fee) | C10: =C5*C6*C8*C9 -> 120000 | D10: =D5*D6*D8*D9 -> 360000 | E10: =E5*E6*E8*E9 -> 600000 | F10: =F5*F6*F8*F9 -> 900000 | G10: =G5*G6*G8*G9 -> 1200000 | H10: =H5*H6*H8*H9 -> 0 | I10: =I5*I6*I8*I9 -> 0 | J10: =J5*J6*J8*J9 -> 0
B11: Major-tournament sponsorship inventory (extra matches x sessions x fee) | C11: =C7*C8*C9 -> 0 | D11: =D7*D8*D9 -> 210000 | E11: =E7*E8*E9 -> 75000 | F11: =F7*F8*F9 -> 0 | G11: =G7*G8*G9 -> 0 | H11: =H7*H8*H9 -> 0 | I11: =I7*I8*I9 -> 0 | J11: =J7*J8*J9 -> 0
B12: Olympic sponsorship inventory (37 venues x 17 days x 3 sessions x fee) | C12: 0 | D12: 0 | E12: 0 | F12: 0 | G12: 0 | H12: =Assumptions!$C$9*Assumptions!$C$10*Assumptions!$C$14*Assumptions!$C$17 -> 6290000 | I12: 0 | J12: 0
B13: Total Sponsorship Inventory Generated (100%, before revenue share) | C13: =SUM(C10:C12) -> 120000 | D13: =SUM(D10:D12) -> 570000 | E13: =SUM(E10:E12) -> 675000 | F13: =SUM(F10:F12) -> 900000 | G13: =SUM(G10:G12) -> 1200000 | H13: =SUM(H10:H12) -> 6290000 | I13: =SUM(I10:I12) -> 0 | J13: =SUM(J10:J12) -> 0
B15: Play the Games revenue share % (of sponsorship inventory) | C15: =Assumptions!$C$19 -> 0.2 | D15: =Assumptions!$C$19 -> 0.2 | E15: =Assumptions!$C$19 -> 0.2 | F15: =Assumptions!$C$19 -> 0.2 | G15: =Assumptions!$C$19 -> 0.2 | H15: =Assumptions!$C$19 -> 0.2 | I15: =Assumptions!$C$19 -> 0.2 | J15: =Assumptions!$C$19 -> 0.2 | K15: PLACEHOLDER - to be negotiated per venue. See Assumptions sheet.
B16: Play the Games Sponsorship Revenue | C16: =C13*C15 -> 24000 | D16: =D13*D15 -> 114000 | E16: =E13*E15 -> 135000 | F16: =F13*F15 -> 180000 | G16: =G13*G15 -> 240000 | H16: =H13*H15 -> 1258000 | I16: =I13*I15 -> 0 | J16: =J13*J15 -> 0
B18: Concession & Redemption Revenue
B19: Estimated active players per session (avg.) | C19: 1500 | D19: 2500 | E19: 3500 | F19: 5000 | G19: 7000 | H19: 25000 | I19: 0 | J19: 0 | K19: Directional estimate of unique players per dead-time session per venue (not total venue attendance); scales with venue count and 2032 Olympic crowd size.
B20: Total sessions run in year (venues x events x sessions + tournament/Olympic sessions) | C20: =(C5*C6+C7)*C8 -> 60 | D20: =(D5*D6+D7)*D8 -> 190 | E20: =(E5*E6+E7)*E8 -> 225 | F20: =(F5*F6+F7)*F8 -> 300 | G20: =(G5*G6+G7)*G8 -> 400 | H20: =Assumptions!$C$9*Assumptions!$C$10*Assumptions!$C$14 -> 629 | I20: =(I5*I6+I7)*I8 -> 0 | J20: =(J5*J6+J7)*J8 -> 0
B21: Total redemptions (sessions x active users x redemption rate) | C21: =C20*C19*Assumptions!$C$21 -> 18000 | D21: =D20*D19*Assumptions!$C$21 -> 95000 | E21: =E20*E19*Assumptions!$C$21 -> 157500 | F21: =F20*F19*Assumptions!$C$21 -> 300000 | G21: =G20*G19*Assumptions!$C$21 -> 560000 | H21: =H20*H19*Assumptions!$C$21 -> 3145000 | I21: =I20*I19*Assumptions!$C$21 -> 0 | J21: =J20*J19*Assumptions!$C$21 -> 0
B22: Total concession spend attributable to platform (redemptions x avg. txn value) | C22: =C21*Assumptions!$C$22 -> 216000 | D22: =D21*Assumptions!$C$22 -> 1140000 | E22: =E21*Assumptions!$C$22 -> 1890000 | F22: =F21*Assumptions!$C$22 -> 3600000 | G22: =G21*Assumptions!$C$22 -> 6720000 | H22: =H21*Assumptions!$C$22 -> 37740000 | I22: =I21*Assumptions!$C$22 -> 0 | J22: =J21*Assumptions!$C$22 -> 0
B23: Play the Games Concession Revenue (share of uplift) | C23: =C22*Assumptions!$C$20 -> 21600 | D23: =D22*Assumptions!$C$20 -> 114000 | E23: =E22*Assumptions!$C$20 -> 189000 | F23: =F22*Assumptions!$C$20 -> 360000 | G23: =G22*Assumptions!$C$20 -> 672000 | H23: =H22*Assumptions!$C$20 -> 3774000 | I23: =I22*Assumptions!$C$20 -> 0 | J23: =J22*Assumptions!$C$20 -> 0
B25: Post-Games Licensing Revenue
B26: AFL licensing fee | C26: 0 | D26: 0 | E26: 0 | F26: 0 | G26: 0 | H26: 0 | I26: =Assumptions!$C$23 -> 500000 | J26: =Assumptions!$C$23 -> 500000
B27: NRL licensing fee | C27: 0 | D27: 0 | E27: 0 | F27: 0 | G27: 0 | H27: 0 | I27: =Assumptions!$C$24 -> 500000 | J27: =Assumptions!$C$24 -> 500000
B28: Cricket Australia licensing fee | C28: 0 | D28: 0 | E28: 0 | F28: 0 | G28: 0 | H28: 0 | I28: =Assumptions!$C$25 -> 300000 | J28: =Assumptions!$C$25 -> 300000
B29: International / other code licensing (combined) | C29: 0 | D29: 0 | E29: 0 | F29: 0 | G29: 0 | H29: 0 | I29: =Assumptions!$C$26 -> 400000 | J29: =Assumptions!$C$26 -> 400000
B30: Total Licensing Revenue | C30: =SUM(C26:C29) -> 0 | D30: =SUM(D26:D29) -> 0 | E30: =SUM(E26:E29) -> 0 | F30: =SUM(F26:F29) -> 0 | G30: =SUM(G26:G29) -> 0 | H30: =SUM(H26:H29) -> 0 | I30: =SUM(I26:I29) -> 1700000 | J30: =SUM(J26:J29) -> 1700000
B32: TOTAL ANNUAL REVENUE | C32: =SUM(C16,C23,C30) -> 45600 | D32: =SUM(D16,D23,D30) -> 228000 | E32: =SUM(E16,E23,E30) -> 324000 | F32: =SUM(F16,F23,F30) -> 540000 | G32: =SUM(G16,G23,G30) -> 912000 | H32: =SUM(H16,H23,H30) -> 5032000 | I32: =SUM(I16,I23,I30) -> 1700000 | J32: =SUM(J16,J23,J30) -> 1700000

Sheet Revenue new logic
A1: Revenue Build-Up by Year (AUD)
A2: AUD
A3: planned growth p.a. (until 2032) | B3: 0.2 | L3: CAGR for fan engagement industry: 12,8%; we want to grow faster; https://marketintelo.com/report/fan-engagement-platforms-market
A4: Revenue Driver | B4: 2026 | C4: 2027 | D4: 2028 | E4: 2029 | F4: 2030 | G4: 2031 | H4: 2032 | I4: 2033 | J4: 2034 | K4: 2035 | L4: Notes / Source
A5: Cost per Mille (CPM) | C5: =1/0.6 -> 1.6666667 | D5: =1/0.6 -> 1.6666667 | E5: =1/0.6 -> 1.6666667 | F5: =1/0.6 -> 1.6666667 | G5: =1/0.6 -> 1.6666667 | H5: =1/0.6 -> 1.6666667 | I5: 0 | J5: 0 | L5: CPM benchmarks 2025: https://www.netmarvel.com/en/blogs/1347.html
A6: Annual visitor capacity across all venues | C6: =E36 -> 3172122 | D6: =C6*$E$38 -> 3806546.4 | E6: =D6*$E$38 -> 4567855.7 | F6: =E6*$E$38 -> 5481426.8 | G6: =F6*$E$38 -> 6577712.2 | H6: =G6*$E$38+N6+O6 -> 19893255 | I6: =G6*$E$38*$E$38 -> 9471905.5 | J6: =I6*$E$38 -> 11366287 | K6: =J6*$E$38 -> 13639544 | L6: research on stadium sides of queensland; presentattion of brendan keane: 9,5+2,5 | N6: 9500000 | O6: 2500000
A7: Sessions per event (dead-time windows) | C7: =Assumptions!$C$14 -> 1 | D7: =Assumptions!$C$14 -> 1 | E7: =Assumptions!$C$14 -> 1 | F7: =Assumptions!$C$14 -> 1 | G7: =Assumptions!$C$14 -> 1 | H7: =Assumptions!$C$14 -> 1 | I7: =Assumptions!$C$14 -> 1 | J7: =Assumptions!$C$14 -> 1 | K7: =Assumptions!$C$14 -> 1 | L7: only once a game
A8: Total Sponsorship Inventory Generated (100%, before revenue share) | C8: =C5*C6*C7 -> 5286870 | D8: =D5*D6*D7 -> 6344244 | E8: =E5*E6*E7 -> 7613092.8 | F8: =F5*F6*F7 -> 9135711.4 | G8: =G5*G6*G7 -> 10962854 | H8: =H5*H6*H7 -> 33155424 | I8: =I5*I6*I7 -> 0 | J8: =J5*J6*J7 -> 0 | K8: =K5*K6*K7 -> 0
A10: Play the Games revenue share % (of sponsorship inventory) | C10: 0.05 | D10: 0.05 | E10: 0.1 | F10: 0.1 | G10: 0.1 | H10: 0.1 | L10: to be negotiated per venue; ticketmaster: 15% https://www.ticketnews.com/2026/04/live-nation-and-ticketmaster-operate-as-an-illegal-monopoly-jury-finds-in-landmark-antitrust-trial/
A11: Play the Games Sponsorship Revenue | C11: =C8*C10 -> 264343.5 | D11: =D8*D10 -> 317212.2 | E11: =E8*E10 -> 761309.28 | F11: =F8*F10 -> 913571.14 | G11: =G8*G10 -> 1096285.4 | H11: =H8*H10 -> 3315542.4 | I11: =I8*I10 -> 0 | J11: =J8*J10 -> 0 | K11: =K8*K10 -> 0
A13: Concession & Redemption Revenue
A14: Estimated active players per session (avg.) | C14: =C6*0.6 -> 1903273.2 | D14: =D6*0.6 -> 2283927.8 | E14: =E6*0.6 -> 2740713.4 | F14: =F6*0.6 -> 3288856.1 | G14: =G6*0.6 -> 3946627.3 | H14: =H6*0.6 -> 11935953 | I14: 0 | J14: 0 | K14: 1 | L14: deloitte study
A15: Total redemptions (sessions x active users x redemption rate) | C15: ?
A16: Total concession spend attributable to platform (redemptions x avg. txn value) | C16: ?
A17: Play the Games Concession Revenue (share of uplift) | C17: =C16*Assumptions!$C$20 -> #VALUE! | D17: =D16*Assumptions!$C$20 -> 0 | E17: =E16*Assumptions!$C$20 -> 0 | F17: =F16*Assumptions!$C$20 -> 0 | G17: =G16*Assumptions!$C$20 -> 0 | H17: =H16*Assumptions!$C$20 -> 0 | I17: =I16*Assumptions!$C$20 -> 0 | J17: =J16*Assumptions!$C$20 -> 0 | K17: =K16*Assumptions!$C$20 -> 0
A19: Post-Games Licensing Revenue
A20: AFL licensing fee | C20: 0 | D20: 0 | E20: 0 | F20: 0 | G20: 0 | H20: 0 | I20: =Assumptions!$C$23 -> 500000 | J20: =Assumptions!$C$23 -> 500000 | K20: =Assumptions!$C$23 -> 500000 | L20: Flat fee replaces the per-event revenue share model; offering the code cost certainty and Play the Games predictable recurring revenue. Fee set conservatively below estimated annual revenue share equivalent.
A21: NRL licensing fee | C21: 0 | D21: 0 | E21: 0 | F21: 0 | G21: 0 | H21: 0 | I21: =Assumptions!$C$24 -> 500000 | J21: =Assumptions!$C$24 -> 500000 | K21: =Assumptions!$C$24 -> 500000
A22: Cricket Australia licensing fee | C22: 0 | D22: 0 | E22: 0 | F22: 0 | G22: 0 | H22: 0 | I22: =Assumptions!$C$25 -> 300000 | J22: =Assumptions!$C$25 -> 300000 | K22: =Assumptions!$C$25 -> 300000
A23: International / other code licensing (combined) | C23: 0 | D23: 0 | E23: 0 | F23: 0 | G23: 0 | H23: 0 | I23: =Assumptions!$C$26 -> 400000 | J23: =Assumptions!$C$26 -> 400000 | K23: =Assumptions!$C$26 -> 400000
A24: Total Licensing Revenue | C24: =SUM(C20:C23) -> 0 | D24: =SUM(D20:D23) -> 0 | E24: =SUM(E20:E23) -> 0 | F24: =SUM(F20:F23) -> 0 | G24: =SUM(G20:G23) -> 0 | H24: =SUM(H20:H23) -> 0 | I24: =SUM(I20:I23) -> 1700000 | J24: =SUM(J20:J23) -> 1700000 | K24: =SUM(K20:K23) -> 1700000
A26: TOTAL ANNUAL REVENUE | C26: =C11 -> 264343.5 | D26: =SUM(D11,D17,D24) -> 317212.2 | E26: =SUM(E11,E17,E24) -> 761309.28 | F26: =SUM(F11,F17,F24) -> 913571.14 | G26: =SUM(G11,G17,G24) -> 1096285.4 | H26: =SUM(H11,H17,H24) -> 3315542.4 | I26: =SUM(I11,I17,I24) -> 1700000 | J26: =SUM(J11,J17,J24) -> 1700000 | K26: =SUM(K11,K17,K24) -> 1700000
B28: Stadiums of Queensland
B29: No. Events (07-12/2026) | D29: Seats
B30: 9 | C30: 2 | D30: 27794 | E30: =B30*C30*D30 -> 500292
B31: 4 | C31: 2 | D31: 27500 | E31: =B31*C31*D31 -> 220000
B32: 5 | C32: 2 | D32: 42000 | E32: =B32*C32*D32 -> 420000
B33: 12 | C33: 2 | D33: 52500 | E33: =B33*C33*D33 -> 1260000
B34: 13 | C34: 2 | D34: 25455 | E34: =B34*C34*D34 -> 661830
B35: 11 | C35: 2 | D35: 5000 | E35: =B35*C35*D35 -> 110000
E36: =SUM(E30:E35) -> 3172122
B38: planned annually growth (till 2032) | E38: 1.2

Sheet Cost-Benefit Summary
A1: Cost-Benefit Summary (AUD)
A3: Line | B3: 2026 | C3: 2027 | D3: 2028 | E3: 2029 | F3: 2030 | G3: 2031 | H3: 2032 | I3: 2033 | J3: 2034 | K3: 2035 | L3: cum | M3: Notes
A4: Total Revenue | B4: 0 | C4: ='Revenue new logic'!C11 -> 264343.5 | D4: ='Revenue new logic'!D11 -> 317212.2 | E4: ='Revenue new logic'!E11 -> 761309.28 | F4: ='Revenue new logic'!F11 -> 913571.14 | G4: ='Revenue new logic'!G11 -> 1096285.4 | H4: ='Revenue new logic'!H11 -> 3315542.4 | I4: ='Revenue new logic'!I24 -> 1700000 | J4: ='Revenue new logic'!J24 -> 1700000 | K4: ='Revenue new logic'!K24 -> 1700000 | L4: =SUM(B4:K4) -> 11768264 | M4: =SUM(B4:K4) -> 11768264
A5: Total Cost | B5: ='Cost Build-Up'!B16 -> 360000 | C5: ='Cost Build-Up'!C16 -> 512200 | D5: ='Cost Build-Up'!D16 -> 527200 | E5: ='Cost Build-Up'!E16 -> 537200 | F5: ='Cost Build-Up'!F16 -> 572200 | G5: ='Cost Build-Up'!G16 -> 577200 | H5: ='Cost Build-Up'!H16 -> 567200 | I5: ='Cost Build-Up'!I16 -> 542200 | ... K5: ='Cost Build-Up'!K16 -> 542200 | L5: =SUM(B5:K5) -> 5279800 | M5: =SUM(B5:K5) -> 5279800
A7: Net Position (Revenue - Cost) | B7: =B4-B5 -> -360000 | C7: =C4-C5 -> -247856.5 | D7: =D4-D5 -> -209987.8 | E7: =E4-E5 -> 224109.28 | F7: =F4-F5 -> 341371.14 | G7: =G4-G5 -> 519085.36 | H7: =H4-H5 -> 2748342.4 | I7: =I4-I5 -> 1157800 | ... K7: =K4-K5 -> 1157800 | L7: =SUM(B7:K7) -> 6488463.9
A8: Cumulative Net Position | B8: =B7 -> -360000 | C8: =C7+B8 -> -607856.5 | D8: =C8+D7 -> -817844.3 | E8: =D8+E7 -> -593735.02 | F8: =E8+F7 -> -252363.88 | G8: =F8+G7 -> 266721.48 | H8: =G8+H7 -> 3015063.9 | I8: =H8+I7 -> 4172863.9 | J8: =I8+J7 -> 5330663.9 | K8: =J8+K7 -> 6488463.9 | M8: =K8/M5 -> 1.2289223
D9: Required Total Investment | K9: ROI: | L9: =L7/L5 -> 1.2289223
A11: Net Margin (%) | B11: =IFERROR(B7/B4,"-") -> - | C11: =IFERROR(C7/C4,"-") -> -0.93763039 | D11: =IFERROR(D7/D4,"-") -> -0.66197895 | E11: =IFERROR(E7/E4,"-") -> 0.2943735 | F11: =IFERROR(F7/F4,"-") -> 0.37366673 | G11: =IFERROR(G7/G4,"-") -> 0.47349475 | H11: =IFERROR(H7/H4,"-") -> 0.82892694 | I11: =IFERROR(I7/I4,"-") -> 0.68105882 | ... K11: =IFERROR(K7/K4,"-") -> 0.68105882
A13: Commentary
A14: Year 1 (2027) is the highest-cost, lowest-revenue year by design - the one-time platform build ($150k) plus QR and redemption system build ($50k combined) are absorbed up-front, against a small 3-venue pilot. This is consistent with the team's phased rollout strategy: validate small, then scale.
A16: From 2028 onward, the model shows costs growing roughly in line with venue count and event complexity, while one-time build costs disappear entirely (replaced by a much smaller annual maintenance line at ~20% of build cost). This is the core economic argument for the business: a single upfront build with low marginal cost per additional venue.
A18: 2032 is the standout year in both directions: Olympic-scale sponsorship inventory at a premium per-session rate drives a sharp revenue spike, while operations and infrastructure costs also spike (37 venues, 17 days, 30,000+ simultaneous users).
A20: 2033-2034 shifts the revenue model from revenue-share sponsorship to flat annual licensing fees paid by AFL, NRL, Cricket Australia and other codes - a more predictable, lower-cost-to-serve revenue stream once the platform is proven.
A22: The single most important unresolved variable in this model is the Play the Games revenue share % (currently a placeholder on the Assumptions sheet, highlighted in yellow). Every revenue figure in this workbook scales directly with that percentage once it is negotiated with real venue partners.
A65: ROI
A66: Initial Invest
A67: Break Even

Sheet Sources
B2: Reference Sources Used in This Model
B4: Note | C4: Play the Games has no direct, publicly-benchmarked precedent operating at this exact scale and model in Australia. The sources below are the closest available real-world proxies for each cost/revenue category and were used to sense-check assumptions, not as exact quotes. Every figure should be validated with real vendor/venue quotes before being used in a binding financial commitment.
B6: Category | C6: Source
B7: In-venue/stadium digital advertising pricing benchmarks | C7: AdQuick, "Stadium, Arena & Sports Team Advertising": entry-level placements ~$1,000/game; digital scoreboard/jumbotron $10,000-$100,000/season; naming rights $500,000-$20M+/year. https://www.adquick.com/stadium-advertising
B8: In-venue LED/perimeter advertising pricing benchmarks | C8: DOIT Vision, "How Much Does a Stadium/Perimeter LED Display Cost?": perimeter LED ad styles $6,000-$15,000 per game. https://www.doitvision.com/how-much-does-perimeter-led-display-cost/
B9: Premium digital board pricing (US major venues, for Olympic-tier rate benchmarking) | C9: Carvertise, "Los Angeles Stadium Advertising": SoFi Stadium LED signage from $200,000+/season; Crypto.com Arena digital boards $75,000-$250,000/season; Dodger Stadium outfield signage $80,000-$250,000/season. https://carvertise.com/los-angeles-stadium-advertising/
B10: LED display ROI/revenue benchmarks | C10: LED Screen Factory, "Stadium LED Screen Cost Guide 2026", citing SportsPro Media's 2024 Stadium Revenue Report: digital perimeter boards can generate $500,000-$3,000,000+ annually for top-tier clubs. https://ledscreenfactory.com/stadium-led-screen-cost-guide/
B11: Mobile/web app MVP development cost benchmarks | C11: TechAhead, "Mobile App Development Cost in 2026": MVP/Proof of Concept tier $50,000-$100,000 USD; maintenance 15-20% of build cost annually. https://www.techaheadcorp.com/blog/mobile-app-development-cost-guide/
B12: Mobile/web app MVP development cost benchmarks (secondary) | C12: Netguru, "Mobile App Development Cost: 2026 Complete Guide": median cross-platform MVP cost (200+ apps analysed) = $76,000 USD. https://www.netguru.com/blog/mobile-app-development-cost
B13: App maintenance cost benchmark | C13: Cynoteck, "Mobile App Development Cost in 2026": industry standard maintenance = 15-20% of original development cost per year. https://www.cynoteck.com/blog-post/mobile-app-development-cost
B14: Enterprise platform / licensing fee benchmark (used for post-2032 AFL/NRL licensing estimate) | C14: TechAhead, "Mobile App Development Cost in 2026": Enterprise Platform tier = $250,000-$500,000+ (build cost basis used as a directional proxy for an annual enterprise licence value). https://www.techaheadcorp.com/blog/mobile-app-development-cost-guide/
B15: Stadium dead-time / crowd behaviour patterns (used to justify session timing logic elsewhere in the pitch, referenced for context) | C15: Industry stadium operations commentary (Billfold, Facilities Dive) describing fans remaining seated during play and moving en masse at breaks; halftime windows of 12-15 minutes (NFL ~12 min, NBA ~15 min) as the fixed dead-time unit.
B16: Project brief figures (ticket volume, venue count, competition days, sport list, Pay-Using-Benefit Criteria, phased rollout structure) | C16: Team project brief: "Play the Games - Slice B - Adaptive Fan Experience, Brisbane 2032 and Beyond" (GIC 2026).
